CHANGELOG
LICENSE
MANIFEST.in
README
hob-merge.py
setup.cfg
setup.py
hob/__init__.py
hob/_js.py
hob/_rst.py
hob/_xmlgen.py
hob/cmd.py
hob/extension.py
hob/parser.py
hob/proto.py
hob/script.py
hob/template.py
hob/ui.py
hob/utils.py
hob.egg-info/PKG-INFO
hob.egg-info/SOURCES.txt
hob.egg-info/dependency_links.txt
hob.egg-info/entry_points.txt
hob.egg-info/requires.txt
hob.egg-info/top_level.txt
hob/templates/html-doc/coredoc.css
hob/templates/html-doc/html-doc-footer.mako
hob/templates/html-doc/html-doc-header.mako
hob/templates/html-doc/html-doc-index.mako
hob/templates/html-doc/html-doc-message.mako
hob/templates/html-doc/html-doc-service.mako
hob/templates/html-doc/html-doc-status.mako
hob/templates/js/clientlib_async.js
hob/templates/js/get_message_maps.js
hob/templates/js/js-DOM.mako
hob/templates/js/js-build_application.mako
hob/templates/js/js-client-html.mako
hob/templates/js/js-client.mako
hob/templates/js/js-field-consts.mako
hob/templates/js/js-helper-const-ids.mako
hob/templates/js/js-http-interface.mako
hob/templates/js/js-message-classes.mako
hob/templates/js/js-message-definition.mako
hob/templates/js/js-runtimes.mako
hob/templates/js/js-service-base.mako
hob/templates/js/js-service-implementation.mako
hob/templates/js/js-stp-0-wrapper.mako
hob/templates/js/js-windows.mako
hob/templates/js/json.js
hob/templates/js/logger.js
hob/templates/js/message_maps.js
hob/templates/js/messagebroker.js
hob/templates/js/messagemixin.js
hob/templates/js/namespace.js
hob/templates/js/simpleconsolelogger.js
hob/templates/js/style.css
hob/templates/js/tag_manager.js
hob/templates/js/test_framework.js
hob/templates/js/utils.js
hob/templates/proto/block_options.mako
hob/templates/proto/enum.mako
hob/templates/proto/inline_options.mako
hob/templates/proto/message.mako
hob/templates/proto/package.mako
hob/templates/proto/scope_descriptor.proto
hob/templates/proto/service.mako
hob/templates/proto/google/protobuf/descriptor.proto
hob/templates/rst-doc/package.mako
hob/templates/rst-doc/rst-doc-service-index.mako
hob/templates/rst-doc/rst-doc-service.mako
hob/templates/rst-doc/rst-proto-defs.mako