Metadata-Version: 1.0
Name: hob
Version: 0.3.3
Summary: A multi-language code generator for the Opera Scope Protocol. Code is generated from Google Protocol Buffer definitions.
Home-page: http://bitbucket.org/scope/hob/
Author: Jan Borsodi, Christian Krebs
Author-email: jborsodi@opera.com, chrisk@opera.com
License: New BSD License
Keywords: scope protobuf
Platform: any
Classifier: Development Status :: 4 - Beta
Classifier: Environment :: Console
Classifier: Topic :: Software Development :: Code Generators
Classifier: License :: OSI Approved :: BSD License
Classifier: Operating System :: OS Independent
Classifier: Programming Language :: Python
Classifier: Topic :: Software Development
